pycsvtosqliteroh/__init__.py
pycsvtosqliteroh/__main__.py
pycsvtosqliteroh-0.0.1.dist-info/LICENSE
pycsvtosqliteroh-0.0.1.dist-info/METADATA
pycsvtosqliteroh-0.0.1.dist-info/WHEEL
pycsvtosqliteroh-0.0.1.dist-info/top_level.txt
pycsvtosqliteroh-0.0.1.dist-info/RECORD
