Metadata-Version: 2.1
Name: pycsvtosqliteroh
Version: 0.0.1
Summary: A python module for converting csv files to sqlite and back.
Author: IT-Administrators
Maintainer: IT-Administrators
License: MIT License
Project-URL: Homepage, https://github.com/IT-Administrators/pycsvtosqliteroh
Keywords: csv,sqlite,converting
Classifier: Programming Language :: Python :: 3
Classifier: License :: OSI Approved :: MIT License
Classifier: Operating System :: OS Independent
Requires-Python: >=3.7
License-File: LICENSE
